Design Modules/v1.1/freq_divider_5bit.v
// Programmable frequency divider
module freq_divider_5bit(
  input wire clk,
  input wire reset,
  input wire [3:0]ndiv,
  output reg freq_div_out);
  
  wire [3:0] thresh;
  reg [31:0] counter;
  
 
 // Threshold is programmable and decides the time-period of output
  assign thresh = ndiv >> 1;
  always@(posedge clk or posedge reset ) begin
    if(reset) begin
      counter <= 32'd0;
      freq_div_out <= 0;
    end
    else begin
      if(counter >= thresh) begin
        freq_div_out <= ~freq_div_out;
        counter <= 32'd0;
      end
      else begin
        counter <= counter + 1;
      end
    end
  end   
endmodule

Design Modules/v1.1/dco_5bit.v
// dco module
// Receives the filter output and generates the proportional time-period
module dco_5bit(
  input wire clk,
  input wire reset,
  input wire[4:0] kdco,
  input wire ctrl_sign,
  input wire [4:0]ctrl,
  input wire [4:0]dco_offset,
  input wire [4:0]thresh_val,
  output reg dco_clk);
  
  wire [4:0] ctrl_buf;
  wire ctrl_sign_buf;
  wire [4:0] thresh;
  wire [4:0]thresh_buf;
  wire [5:0] phase;             // Widen phase to 6 bits to avoid overflow
  reg [31:0] counter;           // 32-bit counter for counting cycles

   // Buffer the control input for reset logic
  assign ctrl_buf = (reset) ? 5'd0 : ctrl;
  assign ctrl_sign_buf = (reset) ? 1'b0 : ctrl_sign;

  // Calculate phase (widen to 6 bits to prevent overflow in phase calculation)
  assign phase = ctrl_buf * kdco;  // Multiply control value with DCO constant

  // Modulate the DCO threshold based on phase. Prevent negative threshold values.
  // Use saturation logic to constrain the threshold between valid values (0 to 31 for 5-bit).
  assign thresh_buf = (ctrl_sign_buf) ? (thresh_val + phase)+dco_offset : (thresh_val - phase)+dco_offset;

  // Saturating threshold handling (clamp between 0 and 31)
  assign thresh = (thresh_buf < 5'd0) ? 5'd0 : (thresh_buf > 5'd31) ? 5'd31 : thresh_buf;

  always @(posedge clk or posedge reset) begin
    if (reset) begin
      dco_clk <= 1'b0;
      counter <= 32'd0;
    end else begin
      // Update threshold and toggle DCO clock based on the counter
      if (counter >= thresh) begin
        dco_clk <= ~dco_clk;               // Flip the DCO output when threshold is crossed
        counter <= {27'd0, dco_offset};    // Reset counter using DCO offset (to keep within range)
      end else begin
        counter <= counter + 1;            // Increment counter otherwise
      end
    end
  end

endmodule

Design Modules/v1.1/acs_5bit.v

// 5-bit Adder cum subtractor (ACS)
// Inputs are 5-bit data and their signs 
// Output is addition/subtraction result with sign
module acs_5bit(
  input wire sign_in1,      // Sign bit for input 1
  input wire [4:0] in1,     // 5-bit input 1
  input wire sign_in2,      // Sign bit for input 2
  input wire [4:0] in2,     // 5-bit input 2
  output wire [4:0] sum,    // 5-bit output sum/result
  output wire sign_out      // Sign of the output result
);

  wire [4:0] in1_buf, in2_buf; // Buffers for the inputs, possibly in 2's complement form
  wire [4:0] sbuf;             // Sum buffer (output of addition/subtraction)
  wire [4:0] result;           // Result buffer for 6-bit sum (including sign)
  wire [4:0] min1, min2;
  wire comp;

  // Convert inputs to 2's complement if the sign bit is 1 (negative)
  assign min1 = ~in1 + 1;
  assign min2 = ~in2 + 1;
  assign in1_buf = (sign_in1) ?  min1 : in1; // Adding sign bit (1'b1 or 0)
  assign in2_buf = (sign_in2) ?  min2 : in2; // Adding sign bit (1'b1 or 0)
  
  // Addition or subtraction (result depends on the signs)
  // If we want subtraction, we can invert the second input and add 1 (2's complement form of subtraction)
  assign result = in1_buf + in2_buf; // Subtract if sign_in2 is 1
  
  // Extract the 5-bit sum (ignoring the overflow from 6th bit)
  assign sbuf = result; 
  
  // Sign logic
  assign comp = (in1 > in2) ? 1'b1:1'b0;
  assign sign_out = (sign_in1 & sign_in2)|(sign_in2 & (~comp))|(sign_in1 & comp); 

  // Output the sum, in 2's complement if the result is negative (sign_out = 1)
  assign sum = (sign_out) ? ~sbuf + 1 : sbuf;

endmodule

Design Modules/v0.0/pi_filter_5bit.v

// 5-bit PI filter
// Receives the phase-error and takes its average
`include "acs_5bit.v"
module pi_filter_5bit(
  input wire clk,
  input wire reset,
  input wire error_sign,
  input wire [4:0]error,
  input wire [4:0]alpha_var,
  input wire [4:0]beta_var,
  output [4:0]integ_out,
  output integ_sign,
  output  [4:0]filter_out,
  output  filter_sign);
  
  reg [4:0]integ_store;
  reg integ_store_sign;
  wire [4:0]integ_var;
  wire [4:0]prop_var;
  wire [4:0]integ_out_buf;
  wire integ_sign_buf;
 
 
  //Proportional Path
  assign prop_var = error >> beta_var;

  //integral path
  assign integ_var = error >> alpha_var;
  
  always@(posedge clk or posedge reset) begin
    if(reset) begin
      integ_store <=8'd0;
      integ_store_sign <= 1'b0;
    end
    else begin    
      integ_store <= integ_out;
      integ_store_sign <= integ_sign;
    end   
  end 

  acs_5bit acs0(.sign_in1(error_sign), .in1(integ_var), .sign_in2(integ_store_sign),.in2(integ_store), .sum(integ_out), .sign_out(integ_sign));
  
  //filter_out
  acs_5bit acs1(.sign_in1(error_sign), .in1(prop_var), .sign_in2(integ_sign),.in2(integ_out), .sum(filter_out), .sign_out(filter_sign));
  
endmodule

Design Modules/v0.0/ones_counter_5bit.v

// Ones Counter
// Receives a 32-bit thermometer code and outputs its binary equivalent
module ones_counter_5bit(
  input wire [31:0] data_in,
  output  [4:0] data_out);
    
  wire [4:0]d0,d1,d2,d3,d4,d5,d6,d7,d8,d9,d10, d11,d12,d13,d14,d15,d16,d17,d18,d19,d20,d21, d22,d23,d24,d25,d26,d27,d28,d29,d30,d31 ;
  
  // Copy each bit in 32-bit data to 5-bit bus
  assign d0 = {1'b0,1'b0,1'b0, 1'b0,data_in[0]};
  assign d1 = {1'b0,1'b0,1'b0, 1'b0,data_in[1]};
  assign d2 = {1'b0,1'b0,1'b0, 1'b0,data_in[2]};
  assign d3 = {1'b0,1'b0,1'b0, 1'b0, data_in[3]};
  assign d4 = {1'b0,1'b0,1'b0, 1'b0, data_in[4]};
  assign d5 = {1'b0,1'b0,1'b0, 1'b0, data_in[5]};
  assign d6 = {1'b0,1'b0,1'b0, 1'b0, data_in[6]};
  assign d7 = {1'b0,1'b0,1'b0, 1'b0, data_in[7]};
  assign d8 = {1'b0,1'b0,1'b0, 1'b0,data_in[8]};
  assign d9 = {1'b0,1'b0,1'b0, 1'b0,data_in[9]};
  assign d10 = {1'b0,1'b0,1'b0, 1'b0,data_in[10]};
  assign d11 = {1'b0,1'b0,1'b0, 1'b0, data_in[11]};
  assign d12 = {1'b0,1'b0,1'b0, 1'b0, data_in[12]};
  assign d13 = {1'b0,1'b0,1'b0, 1'b0, data_in[13]};
  assign d14 = {1'b0,1'b0,1'b0, 1'b0, data_in[14]};
  assign d15 = {1'b0,1'b0,1'b0, 1'b0, data_in[15]};
  assign d16 = {1'b0,1'b0,1'b0, 1'b0,data_in[16]};
  assign d17 = {1'b0,1'b0,1'b0, 1'b0,data_in[17]};
  assign d18 = {1'b0,1'b0,1'b0, 1'b0,data_in[18]};
  assign d19 = {1'b0,1'b0,1'b0, 1'b0, data_in[19]};
  assign d20 = {1'b0,1'b0,1'b0, 1'b0, data_in[20]};
  assign d21 = {1'b0,1'b0,1'b0, 1'b0, data_in[21]};
  assign d22 = {1'b0,1'b0,1'b0, 1'b0, data_in[22]};
  assign d23 = {1'b0,1'b0,1'b0, 1'b0, data_in[23]};
  assign d24 = {1'b0,1'b0,1'b0, 1'b0,data_in[24]};
  assign d25 = {1'b0,1'b0,1'b0, 1'b0,data_in[25]};
  assign d26 = {1'b0,1'b0,1'b0, 1'b0, data_in[26]};
  assign d27 = {1'b0,1'b0,1'b0, 1'b0, data_in[27]};
  assign d28 = {1'b0,1'b0,1'b0, 1'b0, data_in[28]};
  assign d29 = {1'b0,1'b0,1'b0, 1'b0, data_in[29]};
  assign d30 = {1'b0,1'b0,1'b0, 1'b0, data_in[30]};
  assign d31 = {1'b0,1'b0,1'b0, 1'b0, data_in[31]};
  
  
 // Add all the ones 
  
  assign data_out = d0 + d1 + d2 + d3 + d4 + d5 + d6 + d7 + d8 + d9 + d10 + d11 + d12 + d13 + d14 + d15 + d16 + d17 + d18 + d19 + d20 + d21 + d22 + d23 + d24 + d25 + d26 + d27 + d28 + d29 + d30 + d31;
 
 
endmodule

Design Modules/v1.2/tdc_sr_5bit.v
//Thermometer coded TDC-based Phase Detector (PD)
// Sequential PD generates up and down signal which is converted to its binary equivalent by TDC
module tdc_sr_5bit(
  input clk,
  input wire reset,
  input wire clk_ref,
  input wire fb_clk,
  output reg[31:0] up_error,
  output reg[31:0] dwn_error);

  reg start;
  reg up,dwn;
  wire reset_trig;

  // 1. Sequential PD: Generate UP,DWN & RESET
  assign reset_trig = reset | up & dwn;
  // 1.1. UP detection
  always@(posedge clk_ref or posedge reset_trig) begin  
    if(reset_trig) begin
      up <= 0; 
    end
    else begin
      up <=1'b1 & start;
    end
  end
  // 1.2. DWN detection
  always@(posedge fb_clk or posedge reset_trig) begin  
    if(reset_trig) begin
      dwn <= 0; 
    end
    else begin
      dwn <=1'b1 & start;
    end
  end

  // 2. TDC Blocks : Convert UP & DWN to thermometer codes 
  always@(posedge clk or posedge reset_trig) begin
    if(reset_trig) begin
      up_error <= 32'd0;
      dwn_error <= 32'd0;
    end
    else begin
      //UP_ERROR : Thermometer code of UP
      up_error[0] <= up;  
      up_error[31:1] <= up_error[30:0];  
      //DWN_ERROR : Thermometer code of UP
      dwn_error[0] <= dwn;  
      dwn_error[31:1] <= dwn_error[30:0]; 
    end      
  end    

  // 3. Start the phase detection after Clock arrival
  always@(posedge clk_ref or posedge reset) begin
    if(reset)
      start <= 1'b0;
    else 
      start <= 1'b1;
  end

endmodule

Design Modules/v1.1/adpll_5bit.v
// 5-bit ADPLL verilog-code
`include "tdc_sr_5bit.v"
`include "ones_counter_5bit.v"
`include "pi_filter_5bit.v"
`include "dco_5bit.v"
`include "freq_divider_5bit.v"

module adpll_5bit(
  input wire clk,
  input wire reset,
  input wire clk_ref,
  input wire [3:0]ndiv,
  input wire[4:0]alpha_var,
  input wire[4:0]beta_var,
  input wire[4:0]dco_offset,
  input wire[4:0]dco_thresh_val,
  input wire[4:0]kdco,
  inout fb_clk,
  output [4:0] integ_out,
  output integ_sign,
  inout  [4:0] filter_out,
  inout  filter_sign,
  inout dco_out);
  
  wire[31:0] up_error, dwn_error;
  wire[4:0] bin_up_error, bin_dwn_error, bin_error;
  wire error_sign;
  wire[4:0] prop_out;
  wire[4:0] cntrl;
  wire freq_div_buf;
  
  //1. Phase Detection
  tdc_sr_5bit i0_tdc( .clk(clk), .reset(reset), .clk_ref(clk_ref), .fb_clk(fb_clk), .up_error(up_error), .dwn_error(dwn_error));
  ones_counter_5bit i1_oc(.data_in(up_error), .data_out(bin_up_error));
  ones_counter_5bit i2_oc(.data_in(dwn_error), .data_out(bin_dwn_error));
  
  //2. Convert the thermometer code to binary
  assign bin_error = bin_up_error - bin_dwn_error ;
  assign error_sign = (bin_dwn_error > bin_up_error) ? 1:0;

  
  //3. Loop filter
  pi_filter_5bit i3_pi_filter( .clk(clk_ref), .reset(reset), .error_sign(error_sign), .error(bin_error), .alpha_var(alpha_var), .beta_var(beta_var), .integ_out(integ_out), .integ_sign(integ_sign), .filter_out(filter_out), .filter_sign(filter_sign));
  
  assign cntrl = filter_out;
  
  //4. dco
  dco_5bit i4_dco(.clk(clk), .reset(reset), .kdco(kdco), .ctrl_sign(filter_sign), .ctrl(cntrl),.dco_offset(dco_offset), .thresh_val(dco_thresh_val),.dco_clk(dco_out));
  
  //5. Frequency divider
  freq_divider_5bit i5_freq_div(.clk(dco_out), .reset(reset), .ndiv(ndiv), .freq_div_out(freq_div_buf));
  
  //6. Mux out the frequecy divider or dco output directly
  assign fb_clk = (ndiv==4'd0)?dco_out:freq_div_buf;
  
endmodule

Design Modules/v1.1/adpll_top.v
// Top level module of adpll as a chip
// In tiny tapeout we can have 8 input, 8 output, 8 bidirectional, clk and rst pins

`include "adpll_5bit.v"
module adpll_top(
  input wire clk,
  input wire rst,  
  input wire clk_ref,
  input wire clr,
  input wire program,
  input wire out_sel,
  input wire [2:0]param_sel, 
  inout fb_clk,
  inout dco_out,
  inout  [4:0]pgm_value,
  output [4:0] dout,
  output sign);
  
  
 
  reg[4:0]alpha_var_buf;
  reg[4:0]beta_var_buf;
  reg[4:0]dco_offset_buf;
  reg[4:0]dco_thresh_buf;
  reg[4:0]kdco_buf;
  reg[3:0]ndiv;
  wire[4:0]filter_out;
  wire[4:0]integ_out;
  wire filter_sign;
  wire integ_sign;
  wire alpha_en, beta_en,dco_offset_en,dco_thresh_en,kdco_en,ndiv_ld;
  
  
  
 
   
   //Program mode : Program all PLL the parameters
   // Programming is done in cycle by cycle manner, where we can sequentially program below
   //  *** frequency divider ***
   //  1. frequency division for frequency divider block
   //  *** Loop Filter parameters ***
   //  2. alpha
   //  3. beta
   //  **** dco parameters ***
   //  4. dco_offst
   //  5. dco_thresold
   //  6. dco_gain
   
   // Select the programming option
   assign ndiv_ld = (program) ? (param_sel==3'd0)?1:0:0;
   assign alpha_en = (program) ? (param_sel==3'd1)?1:0:0;
   assign beta_en = (program) ? (param_sel==3'd2)?1:0:0;
   assign dco_offset_en = (program) ? (param_sel==3'd3)?1:0:0;
   assign dco_thresh_en = (program) ? (param_sel==3'd4)?1:0:0;
   assign kdco_en = (program) ? (param_sel==3'd5)?1:0:0;


   // outputs filter data or integrator's data based on out_sel variable 
   assign {sign, dout} = (out_sel) ?{integ_sign,integ_out}:{filter_sign, filter_out};

  adpll_5bit u0( .clk(clk), .reset(rst), .clk_ref(clk_ref),.ndiv(ndiv),.alpha_var(alpha_var_buf),.beta_var(beta_var_buf),.dco_offset(dco_offset_buf), .dco_thresh_val(dco_thresh_buf), .kdco(kdco_buf), .fb_clk(fb_clk), .integ_out(integ_out), .integ_sign(integ_sign), .filter_out(filter_out),.filter_sign(filter_sign), .dco_out(dco_out));
       
       
  // Perform programming    
   always@(posedge ndiv_ld) begin
     if(~clr) 
       ndiv <= pgm_value[3:0];
   end
   
   always@(posedge alpha_en) begin
     if(~clr)
       alpha_var_buf <= pgm_value;
   end
   
   always@(posedge beta_en) begin
    if(~clr)
      beta_var_buf <= pgm_value;
   end
     
   always@(posedge dco_offset_en) begin
     if(~clr)
       dco_offset_buf <= pgm_value;
   end
         
   always@(posedge dco_thresh_en) begin
     if(~clr) 
       dco_thresh_buf <= pgm_value;
   end    
     
   always@(posedge kdco_en) begin
     if(~clr)
       kdco_buf <= pgm_value;
   end
   
   always@(posedge clr) begin
     alpha_var_buf <= 5'd0;
     beta_var_buf <= 5'd0;
     dco_offset_buf <= 5'd0;
     dco_thresh_buf <= 5'd0;
     kdco_buf <= 5'd0;  
     ndiv <= 4'd0;  
   end
   
   
endmodule

testbenches/adpll_test1.v
`timescale 1ns/1ps
`include "adpll_top.v"

module adpll_test1;
  reg clk ;
  reg rst ;
  reg clk_ref;
  reg clr;
  reg program;
  reg out_sel;
  reg [2:0]param_sel; 
  wire fb_clk;
  wire dco_out;
  reg [4:0]pgm_value;
  wire [4:0] dout;
  wire sign;
  real delay;
  wire [4:0]value;
  wire signal;
  integer fd;  
  
     adpll_top u0( .clk(clk), .rst(rst), .clk_ref(clk_ref),.clr(clr),.program(program), .out_sel(out_sel),.param_sel(param_sel),.fb_clk(fb_clk),.dco_out(dco_out),.pgm_value(value),.dout(dout),.sign(sign));
       
     assign value = pgm_value;
     
     
     always begin
       #10 clk = ~clk;
     end
     
     always begin
       #(delay) clk_ref = ~clk_ref;
     end
     
     initial begin
       fd = $fopen("output.csv","w");
       $dumpfile("adpll_test1.vcd");
       $dumpvars(0,adpll_test1);
       clk = 1'b0;
       clk_ref =1'b0;
       clr = 1'b0;
       out_sel = 1'b0;
       delay = 250;
  
       #1000;
       clr = 1'b1;
       rst = 1'b1;
       #10;
       clr = 1'b0;
       //Ndiv
       program = 1'b1;
       param_sel = 3'd0;
       pgm_value = 5'd0;
       #10;
       //alpha_var
       param_sel = 3'd1;
       pgm_value = 5'd2;
       #10;
       //beta_var
       param_sel = 3'd2;
       pgm_value = 5'd3;
       #10;
       //dco_offset
       param_sel = 3'd3;
       pgm_value = 5'd8;
       #10;
       //dco_threshold
       param_sel = 3'd4;
       pgm_value = 5'd12;
       #10;
       //kdco (dco gain)
       param_sel = 3'd5;
       pgm_value = 5'd1;     
       rst = 1'b0;  
       #100000;
       delay = 200;
   
       #100000;
       
       delay = 250;
       #100000;
       
       delay = 300;
       #100000;

       $fclose(fd);
       $finish;
     end
     
    always@(posedge clk) begin
       $fwrite(fd,"%t,%b\n",$time,fb_clk);
     end   
     
 endmodule

testbenches/adpll_test1.vcd
$date
	Wed Jan 29 18:18:04 2025
$end
$version
	Icarus Verilog
$end
$timescale
	1ps
$end
$scope module adpll_test1 $end
$var wire 5 ! value [4:0] $end
$var wire 1 " sign $end
$var wire 1 # fb_clk $end
$var wire 5 $ dout [4:0] $end
$var wire 1 % dco_out $end
$var reg 1 & clk $end
$var reg 1 ' clk_ref $end
$var reg 1 ( clr $end
$var reg 1 ) out_sel $end
$var reg 3 * param_sel [2:0] $end
$var reg 5 + pgm_value [4:0] $end
$var reg 1 , program $end
$var reg 1 - rst $end
$var real 1 . delay $end
$var integer 32 / fd [31:0] $end
$scope module u0 $end
$var wire 1 & clk $end
$var wire 1 ' clk_ref $end
$var wire 1 ( clr $end
$var wire 1 ) out_sel $end
$var wire 3 0 param_sel [2:0] $end
$var wire 5 1 pgm_value [4:0] $end
$var wire 1 , program $end
$var wire 1 - rst $end
$var wire 1 " sign $end
$var wire 1 2 ndiv_ld $end
$var wire 1 3 kdco_en $end
$var wire 1 4 integ_sign $end
$var wire 5 5 integ_out [4:0] $end
$var wire 1 6 filter_sign $end
$var wire 5 7 filter_out [4:0] $end
$var wire 1 # fb_clk $end
$var wire 5 8 dout [4:0] $end
$var wire 1 9 dco_thresh_en $end
$var wire 1 % dco_out $end
$var wire 1 : dco_offset_en $end
$var wire 1 ; beta_en $end
$var wire 1 < alpha_en $end
$var reg 5 = alpha_var_buf [4:0] $end
$var reg 5 > beta_var_buf [4:0] $end
$var reg 5 ? dco_offset_buf [4:0] $end
$var reg 5 @ dco_thresh_buf [4:0] $end
$var reg 5 A kdco_buf [4:0] $end
$var reg 4 B ndiv [3:0] $end
$scope module u0 $end
$var wire 5 C alpha_var [4:0] $end
$var wire 5 D beta_var [4:0] $end
$var wire 1 & clk $end
$var wire 1 ' clk_ref $end
$var wire 5 E cntrl [4:0] $end
$var wire 5 F dco_offset [4:0] $end
$var wire 5 G dco_thresh_val [4:0] $end
$var wire 5 H kdco [4:0] $end
$var wire 4 I ndiv [3:0] $end
$var wire 1 - reset $end
$var wire 32 J up_error [31:0] $end
$var wire 1 4 integ_sign $end
$var wire 5 K integ_out [4:0] $end
$var wire 1 L freq_div_buf $end
$var wire 1 6 filter_sign $end
$var wire 5 M filter_out [4:0] $end
$var wire 1 # fb_clk $end
$var wire 1 N error_sign $end
$var wire 32 O dwn_error [31:0] $end
$var wire 1 % dco_out $end
$var wire 5 P bin_up_error [4:0] $end
$var wire 5 Q bin_error [4:0] $end
$var wire 5 R bin_dwn_error [4:0] $end
$scope module i0_tdc $end
$var wire 1 & clk $end
$var wire 1 ' clk_ref $end
$var wire 1 # fb_clk $end
$var wire 1 - reset $end
$var wire 1 S reset_trig $end
$var reg 1 T dwn $end
$var reg 32 U dwn_error [31:0] $end
$var reg 1 V start $end
$var reg 1 W up $end
$var reg 32 X up_error [31:0] $end
$upscope $end
$scope module i1_oc $end
$var wire 32 Y data_in [31:0] $end
$var wire 5 Z data_out [4:0] $end
$var wire 5 [ d9 [4:0] $end
$var wire 5 \ d8 [4:0] $end
$var wire 5 ] d7 [4:0] $end
$var wire 5 ^ d6 [4:0] $end
$var wire 5 _ d5 [4:0] $end
$var wire 5 ` d4 [4:0] $end
$var wire 5 a d31 [4:0] $end
$var wire 5 b d30 [4:0] $end
$var wire 5 c d3 [4:0] $end
$var wire 5 d d29 [4:0] $end
$var wire 5 e d28 [4:0] $end
$var wire 5 f d27 [4:0] $end
$var wire 5 g d26 [4:0] $end
$var wire 5 h d25 [4:0] $end
$var wire 5 i d24 [4:0] $end
$var wire 5 j d23 [4:0] $end
$var wire 5 k d22 [4:0] $end
$var wire 5 l d21 [4:0] $end
$var wire 5 m d20 [4:0] $end
$var wire 5 n d2 [4:0] $end
$var wire 5 o d19 [4:0] $end
$var wire 5 p d18 [4:0] $end
$var wire 5 q d17 [4:0] $end
$var wire 5 r d16 [4:0] $end
$var wire 5 s d15 [4:0] $end
$var wire 5 t d14 [4:0] $end
$var wire 5 u d13 [4:0] $end
$var wire 5 v d12 [4:0] $end
$var wire 5 w d11 [4:0] $end
$var wire 5 x d10 [4:0] $end
$var wire 5 y d1 [4:0] $end
$var wire 5 z d0 [4:0] $end
$upscope $end
$scope module i2_oc $end
$var wire 32 { data_in [31:0] $end
$var wire 5 | data_out [4:0] $end
$var wire 5 } d9 [4:0] $end
$var wire 5 ~ d8 [4:0] $end
$var wire 5 !" d7 [4:0] $end
$var wire 5 "" d6 [4:0] $end
$var wire 5 #" d5 [4:0] $end
$var wire 5 $" d4 [4:0] $end
$var wire 5 %" d31 [4:0] $end
$var wire 5 &" d30 [4:0] $end
$var wire 5 '" d3 [4:0] $end
$var wire 5 (" d29 [4:0] $end
$var wire 5 )" d28 [4:0] $end
$var wire 5 *" d27 [4:0] $end
$var wire 5 +" d26 [4:0] $end
$var wire 5 ," d25 [4:0] $end
$var wire 5 -" d24 [4:0] $end
$var wire 5 ." d23 [4:0] $end
$var wire 5 /" d22 [4:0] $end
$var wire 5 0" d21 [4:0] $end
$var wire 5 1" d20 [4:0] $end
$var wire 5 2" d2 [4:0] $end
$var wire 5 3" d19 [4:0] $end
$var wire 5 4" d18 [4:0] $end
$var wire 5 5" d17 [4:0] $end
$var wire 5 6" d16 [4:0] $end
$var wire 5 7" d15 [4:0] $end
$var wire 5 8" d14 [4:0] $end
$var wire 5 9" d13 [4:0] $end
$var wire 5 :" d12 [4:0] $end
$var wire 5 ;" d11 [4:0] $end
$var wire 5 <" d10 [4:0] $end
$var wire 5 =" d1 [4:0] $end
$var wire 5 >" d0 [4:0] $end
$upscope $end
$scope module i3_pi_filter $end
$var wire 5 ?" alpha_var [4:0] $end
$var wire 5 @" beta_var [4:0] $end
$var wire 1 ' clk $end
$var wire 5 A" error [4:0] $end
$var wire 1 N error_sign $end
$var wire 1 - reset $end
$var wire 5 B" prop_var [4:0] $end
$var wire 5 C" integ_var [4:0] $end
$var wire 1 4 integ_sign $end
$var wire 5 D" integ_out [4:0] $end
$var wire 1 6 filter_sign $end
$var wire 5 E" filter_out [4:0] $end
$var reg 5 F" integ_store [4:0] $end
$var reg 1 G" integ_store_sign $end
$scope module acs0 $end
$var wire 5 H" in1 [4:0] $end
$var wire 5 I" in2 [4:0] $end
$var wire 5 J" sbuf [4:0] $end
$var wire 1 N sign_in1 $end
$var wire 1 G" sign_in2 $end
$var wire 1 4 sign_out $end
$var wire 5 K" sum [4:0] $end
$var wire 5 L" result [4:0] $end
$var wire 5 M" min2 [4:0] $end
$var wire 5 N" min1 [4:0] $end
$var wire 5 O" in2_buf [4:0] $end
$var wire 5 P" in1_buf [4:0] $end
$var wire 1 Q" comp $end
$upscope $end
$scope module acs1 $end
$var wire 5 R" in1 [4:0] $end
$var wire 5 S" in2 [4:0] $end
$var wire 5 T" sbuf [4:0] $end
$var wire 1 N sign_in1 $end
$var wire 1 4 sign_in2 $end
$var wire 1 6 sign_out $end
$var wire 5 U" sum [4:0] $end
$var wire 5 V" result [4:0] $end
$var wire 5 W" min2 [4:0] $end
$var wire 5 X" min1 [4:0] $end
$var wire 5 Y" in2_buf [4:0] $end
$var wire 5 Z" in1_buf [4:0] $end
$var wire 1 [" comp $end
$upscope $end
$upscope $end
$scope module i4_dco $end
$var wire 1 & clk $end
$var wire 5 \" ctrl [4:0] $end
$var wire 1 6 ctrl_sign $end
$var wire 5 ]" dco_offset [4:0] $end
$var wire 5 ^" kdco [4:0] $end
$var wire 1 - reset $end
$var wire 5 _" thresh_val [4:0] $end
$var wire 5 `" thresh_buf [4:0] $end
$var wire 5 a" thresh [4:0] $end
$var wire 6 b" phase [5:0] $end
$var wire 1 c" ctrl_sign_buf $end
$var wire 5 d" ctrl_buf [4:0] $end
$var reg 32 e" counter [31:0] $end
$var reg 1 % dco_clk $end
$upscope $end
$scope module i5_freq_div $end
$var wire 1 % clk $end
$var wire 4 f" ndiv [3:0] $end
$var wire 1 - reset $end
$var wire 4 g" thresh [3:0] $end
$var reg 32 h" counter [31:0] $end
$var reg 1 L freq_div_out $end
$upscope $end
$upscope $end
$upscope $end
$upscope $end
$enddefinitions $end
#0
$dumpvars
bx h"
b0xxx g"
bx f"
bx e"
bx d"
xc"
bx b"
bx a"
bx `"
bx _"
bx ^"
bx ]"
bx \"
x["
bx Z"
bx Y"
bx X"
bx W"
bx V"
bx U"
bx T"
bx S"
bx R"
xQ"
bx P"
bx O"
bx N"
bx M"
bx L"
bx K"
bx J"
bx I"
bx H"
xG"
bx F"
bx E"
bx D"
bx C"
bx B"
bx A"
bx @"
bx ?"
b0x >"
b0x ="
b0x <"
b0x ;"
b0x :"
b0x 9"
b0x 8"
b0x 7"
b0x 6"
b0x 5"
b0x 4"
b0x 3"
b0x 2"
b0x 1"
b0x 0"
b0x /"
b0x ."
b0x -"
b0x ,"
b0x +"
b0x *"
b0x )"
b0x ("
b0x '"
b0x &"
b0x %"
b0x $"
b0x #"
b0x ""
b0x !"
b0x ~
b0x }
bx |
bx {
b0x z
b0x y
b0x x
b0x w
b0x v
b0x u
b0x t
b0x s
b0x r
b0x q
b0x p
b0x o
b0x n
b0x m
b0x l
b0x k
b0x j
b0x i
b0x h
b0x g
b0x f
b0x e
b0x d
b0x c
b0x b
b0x a
b0x `
b0x _
b0x ^
b0x ]
b0x \
b0x [
bx Z
bx Y
bx X
xW
1V
bx U
xT
xS
bx R
bx Q
bx P
bx O
xN
bx M
xL
bx K
bx J
bx I
bx H
bx G
bx F
bx E
bx D
bx C
bx B
bx A
bx @
bx ?
bx >
bx =
x<
x;
x:
x9
bx 8
bx 7
x6
bx 5
x4
x3
x2
bx 1
bx 0
b10000000000000000000000000000011 /
r250 .
x-
x,
bx +
bx *
0)
0(
1'
0&
x%
bx $
x#
x"
bx !
$end
#10000
1&
#20000
0&
#30000
1&
#40000
0&
#50000
1&
#60000
0&
#70000
1&
#80000
0&
#90000
1&
#100000
0&
#110000
1&
#120000
0&
#130000
1&
#140000
0&
#150000
1&
#160000
0&
#170000
1&
#180000
0&
#190000
1&
#200000
0&
#210000
1&
#220000
0&
#230000
1&
#240000
0&
#250000
1&
0'
#260000
0&
#270000
1&
#280000
0&
#290000
1&
#300000
0&
#310000
1&
#320000
0&
#330000
1&
#340000
0&
#350000
1&
#360000
0&
#370000
1&
#380000
0&
#390000
1&
#400000
0&
#410000
1&
#420000
0&
#430000
1&
#440000
0&
#450000
1&
#460000
0&
#470000
1&
#480000
0&
#490000
1&
#500000
1W
0&
1'
#510000
b1 z
bx1 J
bx1 X
bx1 Y
1&
#520000
0&
#530000
b1 y
bx11 J
bx11 X
bx11 Y
1&
#540000
0&
#550000
b1 n
bx111 J
bx111 X
bx111 Y
1&
#560000
0&
#570000
b1 c
bx1111 J
bx1111 X
bx1111 Y
1&
#580000
0&
#590000
b1 `
bx11111 J
bx11111 X
bx11111 Y
1&
#600000
0&
#610000
b1 _
bx111111 J
bx111111 X
bx111111 Y
1&
#620000
0&
#630000
b1 ^
bx1111111 J
bx1111111 X
bx1111111 Y
1&
#640000
0&
#650000
b1 ]
bx11111111 J
bx11111111 X
bx11111111 Y
1&
#660000
0&
#670000
b1 \
bx111111111 J
bx111111111 X
bx111111111 Y
1&
#680000
0&
#690000
b1 [
bx1111111111 J
bx1111111111 X
bx1111111111 Y
1&
#700000
0&
#710000
b1 x
bx11111111111 J
bx11111111111 X
bx11111111111 Y
1&
#720000
0&
#730000
b1 w
bx111111111111 J
bx111111111111 X
bx111111111111 Y
1&
#740000
0&
#750000
b1 v
bx1111111111111 J
bx1111111111111 X
bx1111111111111 Y
1&
0'
#760000
0&
#770000
b1 u
bx11111111111111 J
bx11111111111111 X
bx11111111111111 Y
1&
#780000
0&
#790000
b1 t
bx111111111111111 J
bx111111111111111 X
bx111111111111111 Y
1&
#800000
0&
#810000
b1 s
bx1111111111111111 J
bx1111111111111111 X
bx1111111111111111 Y
1&
#820000
0&
#830000
b1 r
bx11111111111111111 J
bx11111111111111111 X
bx11111111111111111 Y
1&
#840000
0&
#850000
b1 q
bx111111111111111111 J
bx111111111111111111 X
bx111111111111111111 Y
1&
#860000
0&
#870000
b1 p
bx1111111111111111111 J
bx1111111111111111111 X
bx1111111111111111111 Y
1&
#880000
0&
#890000
b1 o
bx11111111111111111111 J
bx11111111111111111111 X
bx11111111111111111111 Y
1&
#900000
0&
#910000
b1 m
bx111111111111111111111 J
bx111111111111111111111 X
bx111111111111111111111 Y
1&
#920000
0&
#930000
b1 l
bx1111111111111111111111 J
bx1111111111111111111111 X
bx1111111111111111111111 Y
1&
#940000
0&
#950000
b1 k
bx11111111111111111111111 J
bx11111111111111111111111 X
bx11111111111111111111111 Y
1&
#960000
0&
#970000
b1 j
bx111111111111111111111111 J
bx111111111111111111111111 X
bx111111111111111111111111 Y
1&
#980000
0&
#990000
b1 i
bx1111111111111111111111111 J
bx1111111111111111111111111 X
bx1111111111111111111111111 Y
1&
